fperms/__init__.py
fperms/admin.py
fperms/apps.py
fperms/backends.py
fperms/base.py
fperms/conf.py
fperms/enums.py
fperms/exceptions.py
fperms/managers.py
fperms/models.py
fperms/utils.py
fperms/locale/cs/LC_MESSAGES/django.mo
fperms/locale/cs/LC_MESSAGES/django.po
fperms/migrations/0001_initial.py
fperms/migrations/0002_auto_20180713_1450.py
fperms/migrations/0003_migration.py
fperms/migrations/0004_migration.py
fperms/migrations/0005_migration.py
fperms/migrations/__init__.py
fperms/static/css/django_perms.css
fperms/static/js/django_perms.js
fperms/templates/django_perms/base.html
skip_django_fperms-0.5.0.dist-info/AUTHORS.rst
skip_django_fperms-0.5.0.dist-info/LICENSE
skip_django_fperms-0.5.0.dist-info/METADATA
skip_django_fperms-0.5.0.dist-info/WHEEL
skip_django_fperms-0.5.0.dist-info/top_level.txt
skip_django_fperms-0.5.0.dist-info/RECORD
