Metadata-Version: 2.1
Name: skip-django-fperms
Version: 0.5.0
Summary: Flexible Django permissions backend
Home-page: https://github.com/skip-pay/django-fperms
Download-URL: https://github.com/skip-pay/django-fperms/archive/0.5.0.tar.gz
Author: Petr Olah
Author-email: djangoguru@gmail.com
License: MIT
Keywords: django-fperms
Classifier: Development Status :: 3 - Alpha
Classifier: Framework :: Django
Classifier: Framework :: Django :: 1.11
Classifier: Framework :: Django :: 2.0
Classifier: Intended Audience :: Developers
Classifier: License :: OSI Approved :: BSD License
Classifier: Natural Language :: English
Classifier: Programming Language :: Python :: 3
Classifier: Programming Language :: Python :: 3.5
Classifier: Programming Language :: Python :: 3.6
License-File: LICENSE
License-File: AUTHORS.rst
Requires-Dist: django >=4.2.0
